reference_playback/__init__.py
reference_playback/api_calls.py
reference_playback/asyn_http_request.py
reference_playback-0.0.3.dist-info/LICENSE
reference_playback-0.0.3.dist-info/METADATA
reference_playback-0.0.3.dist-info/WHEEL
reference_playback-0.0.3.dist-info/top_level.txt
reference_playback-0.0.3.dist-info/RECORD
